{"trial_id": "ed3c1ed07278a6e122ae5165a106580b", "hyperparameters": {"space": [{"class_name": "Int", "config": {"name": "units1", "default": null, "conditions": [], "min_value": 50, "max_value": 400, "step": 50, "sampling": null}}, {"class_name": "Int", "config": {"name": "units2", "default": null, "conditions": [], "min_value": 50, "max_value": 400, "step": 50, "sampling": null}}, {"class_name": "Choice", "config": {"name": "learning_rate", "default": 0.001, "conditions": [], "values": [0.001, 0.01, 0.1, 0.2, 0.3], "ordered": true}}], "values": {"units1": 100, "units2": 200, "learning_rate": 0.1, "tuner/epochs": 2, "tuner/initial_epoch": 0, "tuner/bracket": 6, "tuner/round": 0}}, "metrics": {"metrics": {"loss": {"direction": "min", "observations": [{"value": [0.5688800811767578], "step": 0}]}, "accuracy": {"direction": "max", "observations": [{"value": [0.7429661154747009], "step": 0}]}, "val_loss": {"direction": "min", "observations": [{"value": [0.4046781659126282], "step": 0}]}, "val_accuracy": {"direction": "max", "observations": [{"value": [0.7397521734237671], "step": 0}]}}}, "score": 0.7397521734237671, "best_step": 0, "status": "COMPLETED"}